sumo_logger/__init__.py
sumo_logger/context.py
sumo_logger/handler.py
sumo_logger/setup_logger.py
sumo_logger-1.2.2.dist-info/licenses/LICENSE
sumo_logger-1.2.2.dist-info/METADATA
sumo_logger-1.2.2.dist-info/WHEEL
sumo_logger-1.2.2.dist-info/top_level.txt
sumo_logger-1.2.2.dist-info/RECORD
