Metadata-Version: 2.4
Name: sumo-logger
Version: 1.2.2
Summary: A lightweight Python logging handler for sending logs to Sumo Logic HTTP Sources.
Author-email: Saad Ullah <saadullah.butt@caregenix.solutions>
License: MIT
Requires-Python: >=3.8
License-File: LICENSE
Requires-Dist: requests
Dynamic: license-file
